_icu.cpython-37m-i386-linux-gnu.so
PyICU.py
icu/__init__.py
PyICU_binary.libs/libicudata-1f36471e.so.69.1
PyICU_binary.libs/libicui18n-ac8e57fd.so.69.1
PyICU_binary.libs/libicuuc-dbd42eef.so.69.1
PyICU_binary-2.7.4.dist-info/LICENSE
PyICU_binary-2.7.4.dist-info/top_level.txt
PyICU_binary-2.7.4.dist-info/WHEEL
PyICU_binary-2.7.4.dist-info/RECORD
PyICU_binary-2.7.4.dist-info/METADATA
