Metadata-Version: 2.1
Name: PyICU-binary
Version: 2.7.4
Summary: Python extension wrapping the ICU C++ API
Home-page: https://gitlab.pyicu.org/main/pyicu
Author: Andi Vajda
Author-email: vajda@pyicu.org
License: MIT
Platform: UNKNOWN
Classifier: Development Status :: 5 - Production/Stable
Classifier: Environment :: Console
Classifier: Intended Audience :: Developers
Classifier: License :: OSI Approved
Classifier: Operating System :: OS Independent
Classifier: Programming Language :: C++
Classifier: Programming Language :: Python
Classifier: Programming Language :: Python :: 2
Classifier: Programming Language :: Python :: 3
Classifier: Programming Language :: Python :: Implementation :: CPython
Classifier: Programming Language :: Python :: Implementation :: PyPy
Classifier: Topic :: Software Development :: Localization
Classifier: Topic :: Software Development :: Internationalization
License-File: LICENSE
